msgr.py
Msgr-1.0.0.dist-info/DESCRIPTION.rst
Msgr-1.0.0.dist-info/METADATA
Msgr-1.0.0.dist-info/RECORD
Msgr-1.0.0.dist-info/WHEEL
Msgr-1.0.0.dist-info/metadata.json
Msgr-1.0.0.dist-info/top_level.txt
