Metadata-Version: 2.0
Name: Msgr
Version: 1.0.0
Summary: A Python messaging library.
Home-page: https://www.github.com/copyrighthero/Msgr
Author: Hansheng Zhao
Author-email: copyrighthero@gmail.com
License: BSD-2-Clause + MIT
Download-URL: https://www.github.com/copyrighthero/Msgr
Project-URL: Source, https://www.github.com/copyrighthero/Msgr
Keywords: Python Messaging Library
Platform: UNKNOWN
Classifier: Development Status :: 5 - Production/Stable
Classifier: Intended Audience :: Developers
Classifier: Intended Audience :: End Users/Desktop
Classifier: Intended Audience :: Information Technology
Classifier: Intended Audience :: Science/Research
Classifier: Intended Audience :: System Administrators
Classifier: License :: OSI Approved :: BSD License
Classifier: License :: OSI Approved :: MIT License
Classifier: Natural Language :: English
Classifier: Operating System :: OS Independent
Classifier: Programming Language :: Python :: 2
Classifier: Programming Language :: Python :: 3
Classifier: Topic :: Communications
Classifier: Topic :: Database
Classifier: Topic :: Internet
Classifier: Topic :: Software Development
Classifier: Topic :: System
Classifier: Topic :: Utilities
